fitdecode/__init__.py
fitdecode/__meta__.py
fitdecode/exceptions.py
fitdecode/processors.py
fitdecode/profile.py
fitdecode/reader.py
fitdecode/records.py
fitdecode/types.py
fitdecode/utils.py
fitdecode/cmd/__init__.py
fitdecode/cmd/fitjson.py
fitdecode/cmd/fittxt.py
fitdecode-0.10.0.dist-info/LICENSE.txt
fitdecode-0.10.0.dist-info/METADATA
fitdecode-0.10.0.dist-info/WHEEL
fitdecode-0.10.0.dist-info/entry_points.txt
fitdecode-0.10.0.dist-info/top_level.txt
fitdecode-0.10.0.dist-info/RECORD
