Metadata-Version: 2.1
Name: fitdecode
Version: 0.10.0
Summary: FIT file parser and decoder
Home-page: https://github.com/polyvertex/fitdecode
Author: Jean-Charles Lefebvre
Author-email: polyvertex@gmail.com
License: MIT
Keywords: fit,ant,file,parse,parser,decode,decoder
Platform: UNKNOWN
Classifier: Development Status :: 4 - Beta
Classifier: Intended Audience :: Developers
Classifier: Natural Language :: English
Classifier: License :: OSI Approved :: MIT License
Classifier: Operating System :: OS Independent
Classifier: Programming Language :: Python
Classifier: Programming Language :: Python :: 3
Classifier: Programming Language :: Python :: 3.6
Requires-Python: >=3.6
Provides-Extra: docs
